rasterMiner/__init__.py
rasterMiner/GUI/GUImain.py
rasterMiner/GUI/__init__.py
rasterMiner/GUI/affinityPropagation.py
rasterMiner/GUI/birch.py
rasterMiner/GUI/dbscan.py
rasterMiner/GUI/elbowKmeans.py
rasterMiner/GUI/elbowKmeansPl.py
rasterMiner/GUI/fuzzyKMeans.py
rasterMiner/GUI/kmeans.py
rasterMiner/GUI/meanShift.py
rasterMiner/GUI/optics.py
rasterMiner/GUI/periodicFrequentPattern.py
rasterMiner/GUI/rasterMiner.py
rasterMiner/GUI/spectralClustering.py
rasterMiner/GUI/algorithms/__init__.py
rasterMiner/GUI/algorithms/TimeSeriesClassification-master/1NNDTW.py
rasterMiner/GUI/algorithms/TimeSeriesClassification-master/1NNED.py
rasterMiner/GUI/algorithms/TimeSeriesClassification-master/1NNHausdorff.py
rasterMiner/GUI/algorithms/TimeSeriesClassification-master/1NNmaxinorm.py
rasterMiner/GUI/algorithms/TimeSeriesClassification-master/__init__.py
rasterMiner/GUI/algorithms/TimeSeriesClassification-master/fuzzyTSC.py
rasterMiner/GUI/algorithms/clustering/__init__.py
rasterMiner/GUI/algorithms/clustering/affinitypropagation.py
rasterMiner/GUI/algorithms/clustering/birch.py
rasterMiner/GUI/algorithms/clustering/dbscan.py
rasterMiner/GUI/algorithms/clustering/elbowKmeans.py
rasterMiner/GUI/algorithms/clustering/elbowKmeansPl.py
rasterMiner/GUI/algorithms/clustering/fuzzyKmeans.py
rasterMiner/GUI/algorithms/clustering/kmeans.py
rasterMiner/GUI/algorithms/clustering/meanShift.py
rasterMiner/GUI/algorithms/clustering/optics.py
rasterMiner/GUI/algorithms/clustering/spectralClustering.py
rasterMiner/GUI/algorithms/patternmining/__init__.py
rasterMiner/GUI/algorithms/patternmining/createDB.py
rasterMiner/GUI/algorithms/patternmining/createDenseDF.py
rasterMiner/GUI/algorithms/patternmining/dense2DB.py
rasterMiner/GUI/algorithms/patternmining/euclidDistance.py
rasterMiner/GUI/algorithms/patternmining/runSpatialFPGrowth.py
rasterMiner/GUI/algorithms/patternmining/spatialFPGrowth.py
rasterMiner/GUI/algorithms/patternmining/FPGrowth/__init__.py
RasterMiner-0.1.2.5.dist-info/LICENSE
RasterMiner-0.1.2.5.dist-info/METADATA
RasterMiner-0.1.2.5.dist-info/WHEEL
RasterMiner-0.1.2.5.dist-info/top_level.txt
RasterMiner-0.1.2.5.dist-info/RECORD
