Metadata-Version: 2.1
Name: RasterMiner
Version: 0.1.2.5
Summary: This software is being developed at the University of Aizu, Aizu-Wakamatsu, Fukushima, Japan
Home-page: https://github.com/udayRage/PAMI
Author: Rage Uday Kiran
Author-email: uday.rage@gmail.com
License: GPLv3
Platform: UNKNOWN
Classifier: Development Status :: 3 - Alpha
Classifier: Programming Language :: Python :: 3
Classifier: License :: OSI Approved :: GNU General Public License v3 (GPLv3)
Classifier: Operating System :: OS Independent
Requires-Python: >=3.5
Requires-Dist: psutil
Requires-Dist: pandas
Requires-Dist: matplotlib
Requires-Dist: resource
Requires-Dist: mplcursors
Requires-Dist: sklearn
Requires-Dist: pami
Requires-Dist: sklearn-extensions
Requires-Dist: tk
Requires-Dist: setuptools
Requires-Dist: numpy
Requires-Dist: scikit-learn
